{"cameraMode":{"drawMode":0,"name":"Shaded","section":"Shading Mode"},"sceneLighting":true,"audioPlay":false,"sceneViewState":{"m_AlwaysRefresh":false,"showFog":true,"showSkybox":true,"showFlares":true,"showImageEffects":true,"showParticleSystems":true,"showVisualEffectGraphs":true,"m_FxEnabled":true},"in2DMode":false,"pivot":{"x":377.7245788574219,"y":-521.2794799804688,"z":684.1154174804688},"rotation":{"x":0.32360154390335085,"y":0.16406981647014619,"z":-0.05707012489438057,"w":0.9301299452781677},"size":646.8824462890625,"orthographic":false}